lokzzpylib/__init__.py
lokzzpylib-0.2.dist-info/METADATA
lokzzpylib-0.2.dist-info/WHEEL
lokzzpylib-0.2.dist-info/top_level.txt
lokzzpylib-0.2.dist-info/RECORD
