Metadata-Version: 2.1
Name: lokzzpylib
Version: 0.2
Summary: personal library
Author-email: lokzz <lokzz@github.com>
License: BSD-3-Clause
Classifier: Programming Language :: Python :: 3
Classifier: License :: OSI Approved :: MIT License
Classifier: Operating System :: OS Independent
Requires-Python: >=3
Requires-Dist: colorama
Requires-Dist: keyboard
Requires-Dist: clint
Requires-Dist: numpy
Requires-Dist: pick
